<?xml version="1.0" encoding="utf-8"?>
<Document>
  <Engineering version="V15.1" />
  <DocumentInfo>
    <Created>2020-06-12T07:35:52.6787109Z</Created>
    <ExportSetting>None</ExportSetting>
    <InstalledProducts>
      <Product>
        <DisplayName>Totally Integrated Automation Portal</DisplayName>
        <DisplayVersion>V15.1</DisplayVersion>
      </Product>
      <OptionPackage>
        <DisplayName>TIA Portal Openness</DisplayName>
        <DisplayVersion>V15.1</DisplayVersion>
      </OptionPackage>
      <Product>
        <DisplayName>STEP 7 Professional</DisplayName>
        <DisplayVersion>V15.1</DisplayVersion>
      </Product>
      <OptionPackage>
        <DisplayName>STEP 7 Safety</DisplayName>
        <DisplayVersion>V15.1</DisplayVersion>
      </OptionPackage>
      <Product>
        <DisplayName>WinCC Advanced</DisplayName>
        <DisplayVersion>V15.1</DisplayVersion>
      </Product>
    </InstalledProducts>
  </DocumentInfo>
  <SW.Blocks.FC ID="0">
    <AttributeList>
      <Interface>
        <Sections xmlns="http://www.siemens.com/automation/Openness/SW/Interface/v3">
          <Section Name="Input" />
          <Section Name="Output" />
          <Section Name="InOut" />
          <Section Name="Temp">
            <Member Name="tTmpU" Datatype="Real" />
            <Member Name="tPwrAdd" Datatype="Real" />
            <Member Name="tResAdd" Datatype="Real" />
            <Member Name="tCalcSW" Datatype="Bool" />
            <Member Name="tCalcMR" Datatype="Bool" />
            <Member Name="tCalcPwr" Datatype="Bool" />
            <Member Name="tCalcRes" Datatype="Bool" />
            <Member Name="tVar3" Datatype="Real" />
            <Member Name="tHTPower" Datatype="Real" />
            <Member Name="tHTResistance" Datatype="Real" />
            <Member Name="tPmax" Datatype="Real" />
            <Member Name="tImax" Datatype="Real" />
            <Member Name="tUseST" Datatype="Bool" />
            <Member Name="tUseHT" Datatype="Bool" />
            <Member Name="tCosPhi" Datatype="Real" />
            <Member Name="tUlim" Datatype="Real" />
            <Member Name="tIlim" Datatype="Real" />
            <Member Name="tUseForOCT" Datatype="Bool" />
            <Member Name="tPset_ST" Datatype="Real" />
            <Member Name="tPset_OCT" Datatype="Real" />
          </Section>
          <Section Name="Constant" />
          <Section Name="Return">
            <Member Name="Ret_Val" Datatype="Void" />
          </Section>
        </Sections>
      </Interface>
      <MemoryLayout>Optimized</MemoryLayout>
      <Name>MELT_Setpoints</Name>
      <Number>90</Number>
      <ProgrammingLanguage>FBD</ProgrammingLanguage>
      <SetENOAutomatically>False</SetENOAutomatically>
    </AttributeList>
    <ObjectList>
      <MultilingualText ID="1" CompositionName="Comment">
        <ObjectList>
          <MultilingualTextItem ID="2" CompositionName="Items">
            <AttributeList>
              <Culture>en-US</Culture>
              <Text />
            </AttributeList>
          </MultilingualTextItem>
          <MultilingualTextItem ID="3" CompositionName="Items">
            <AttributeList>
              <Culture>de-DE</Culture>
              <Text />
            </AttributeList>
          </MultilingualTextItem>
        </ObjectList>
      </MultilingualText>
      <SW.Blocks.CompileUnit ID="4" CompositionName="CompileUnits">
        <AttributeList>
          <NetworkSource>
            <FlgNet xmlns="http://www.siemens.com/automation/Openness/SW/NetworkSource/FlgNet/v3">
              <Parts>
                <Access Scope="GlobalVariable" UId="21">
                  <Symbol>
                    <Component Name="MELT_CONT_DB" />
                    <Component Name="mr_clock" />
                  </Symbol>
                </Access>
                <Access Scope="LocalVariable" UId="22">
                  <Symbol>
                    <Component Name="tCalcMR" />
                  </Symbol>
                </Access>
                <Access Scope="LocalVariable" UId="23">
                  <Symbol>
                    <Component Name="tCalcSW" />
                  </Symbol>
                </Access>
                <Part Name="Coil" UId="24" />
                <Part Name="Coil" UId="25" />
              </Parts>
              <Wires>
                <Wire UId="26">
                  <IdentCon UId="21" />
                  <NameCon UId="24" Name="in" />
                </Wire>
                <Wire UId="27">
                  <IdentCon UId="22" />
                  <NameCon UId="24" Name="operand" />
                </Wire>
                <Wire UId="28">
                  <NameCon UId="24" Name="out" />
                  <NameCon UId="25" Name="in" />
                </Wire>
                <Wire UId="29">
                  <IdentCon UId="23" />
                  <NameCon UId="25" Name="operand" />
                </Wire>
              </Wires>
            </FlgNet>
          </NetworkSource>
          <ProgrammingLanguage>FBD</ProgrammingLanguage>
        </AttributeList>
        <ObjectList>
          <MultilingualText ID="5" CompositionName="Comment">
            <ObjectList>
              <MultilingualTextItem ID="6" CompositionName="Items">
                <AttributeList>
                  <Culture>en-US</Culture>
                  <Text />
                </AttributeList>
              </MultilingualTextItem>
              <MultilingualTextItem ID="7" CompositionName="Items">
                <AttributeList>
                  <Culture>de-DE</Culture>
                  <Text />
                </AttributeList>
              </MultilingualTextItem>
            </ObjectList>
          </MultilingualText>
          <MultilingualText ID="8" CompositionName="Title">
            <ObjectList>
              <MultilingualTextItem ID="9" CompositionName="Items">
                <AttributeList>
                  <Culture>en-US</Culture>
                  <Text>Clocks</Text>
                </AttributeList>
              </MultilingualTextItem>
              <MultilingualTextItem ID="A" CompositionName="Items">
                <AttributeList>
                  <Culture>de-DE</Culture>
                  <Text />
                </AttributeList>
              </MultilingualTextItem>
            </ObjectList>
          </MultilingualText>
        </ObjectList>
      </SW.Blocks.CompileUnit>
      <SW.Blocks.CompileUnit ID="B" CompositionName="CompileUnits">
        <AttributeList>
          <NetworkSource>
            <FlgNet xmlns="http://www.siemens.com/automation/Openness/SW/NetworkSource/FlgNet/v3">
              <Parts>
                <Access Scope="LiteralConstant" UId="21">
                  <Constant>
                    <ConstantType>Real</ConstantType>
                    <ConstantValue>0.0</ConstantValue>
                  </Constant>
                </Access>
                <Access Scope="LocalVariable" UId="22">
                  <Symbol>
                    <Component Name="tPwrAdd" />
                  </Symbol>
                </Access>
                <Access Scope="LiteralConstant" UId="23">
                  <Constant>
                    <ConstantType>Real</ConstantType>
                    <ConstantValue>0.0</ConstantValue>
                  </Constant>
                </Access>
                <Access Scope="LocalVariable" UId="24">
                  <Symbol>
                    <Component Name="tResAdd" />
                  </Symbol>
                </Access>
                <Part Name="Move" UId="25" DisabledENO="true">
                  <TemplateValue Name="Card" Type="Cardinality">1</TemplateValue>
                </Part>
                <Part Name="Move" UId="26" DisabledENO="true">
                  <TemplateValue Name="Card" Type="Cardinality">1</TemplateValue>
                </Part>
              </Parts>
              <Wires>
                <Wire UId="29">
                  <OpenCon UId="27" />
                  <NameCon UId="25" Name="en" />
                </Wire>
                <Wire UId="30">
                  <IdentCon UId="21" />
                  <NameCon UId="25" Name="in" />
                </Wire>
                <Wire UId="31">
                  <NameCon UId="25" Name="out1" />
                  <IdentCon UId="22" />
                </Wire>
                <Wire UId="32">
                  <OpenCon UId="28" />
                  <NameCon UId="26" Name="en" />
                </Wire>
                <Wire UId="33">
                  <IdentCon UId="23" />
                  <NameCon UId="26" Name="in" />
                </Wire>
                <Wire UId="34">
                  <NameCon UId="26" Name="out1" />
                  <IdentCon UId="24" />
                </Wire>
              </Wires>
            </FlgNet>
          </NetworkSource>
          <ProgrammingLanguage>FBD</ProgrammingLanguage>
        </AttributeList>
        <ObjectList>
          <MultilingualText ID="C" CompositionName="Comment">
            <ObjectList>
              <MultilingualTextItem ID="D" CompositionName="Items">
                <AttributeList>
                  <Culture>en-US</Culture>
                  <Text />
                </AttributeList>
              </MultilingualTextItem>
              <MultilingualTextItem ID="E" CompositionName="Items">
                <AttributeList>
                  <Culture>de-DE</Culture>
                  <Text />
                </AttributeList>
              </MultilingualTextItem>
            </ObjectList>
          </MultilingualText>
          <MultilingualText ID="F" CompositionName="Title">
            <ObjectList>
              <MultilingualTextItem ID="10" CompositionName="Items">
                <AttributeList>
                  <Culture>en-US</Culture>
                  <Text>dP, dR initial</Text>
                </AttributeList>
              </MultilingualTextItem>
              <MultilingualTextItem ID="11" CompositionName="Items">
                <AttributeList>
                  <Culture>de-DE</Culture>
                  <Text />
                </AttributeList>
              </MultilingualTextItem>
            </ObjectList>
          </MultilingualText>
        </ObjectList>
      </SW.Blocks.CompileUnit>
      <SW.Blocks.CompileUnit ID="12" CompositionName="CompileUnits">
        <AttributeList>
          <NetworkSource>
            <FlgNet xmlns="http://www.siemens.com/automation/Openness/SW/NetworkSource/FlgNet/v3">
              <Parts>
                <Access Scope="GlobalVariable" UId="21">
                  <Symbol>
                    <Component Name="MELT_PAR_DB" />
                    <Component Name="mr_cont_sel" />
                  </Symbol>
                </Access>
                <Access Scope="GlobalVariable" UId="22">
                  <Symbol>
                    <Component Name="MELT_CONT_DB" />
                    <Component Name="mr_out" />
                  </Symbol>
                </Access>
                <Access Scope="GlobalVariable" UId="23">
                  <Symbol>
                    <Component Name="MELT_CONT_DB" />
                    <Component Name="sw_out" />
                  </Symbol>
                </Access>
                <Access Scope="LiteralConstant" UId="24">
                  <Constant>
                    <ConstantType>Real</ConstantType>
                    <ConstantValue>0.0</ConstantValue>
                  </Constant>
                </Access>
                <Access Scope="LocalVariable" UId="25">
                  <Symbol>
                    <Component Name="tPwrAdd" />
                  </Symbol>
                </Access>
                <Access Scope="LocalVariable" UId="26">
                  <Symbol>
                    <Component Name="tResAdd" />
                  </Symbol>
                </Access>
                <Call UId="27">
                  <CallInfo Name="MELT_SET_PR" BlockType="FC">
                    <Parameter Name="iKMR" Section="Input" Type="Real" />
                    <Parameter Name="iKSW" Section="Input" Type="Real" />
                    <Parameter Name="pMA" Section="Input" Type="Real" />
                    <Parameter Name="qKMR" Section="Output" Type="Real" />
                    <Parameter Name="qKSW" Section="Output" Type="Real" />
                  </CallInfo>
                  <Negated Name="en" />
                </Call>
              </Parts>
              <Wires>
                <Wire UId="28">
                  <IdentCon UId="21" />
                  <NameCon UId="27" Name="en" />
                </Wire>
                <Wire UId="29">
                  <IdentCon UId="22" />
                  <NameCon UId="27" Name="iKMR" />
                </Wire>
                <Wire UId="30">
                  <IdentCon UId="23" />
                  <NameCon UId="27" Name="iKSW" />
                </Wire>
                <Wire UId="31">
                  <IdentCon UId="24" />
                  <NameCon UId="27" Name="pMA" />
                </Wire>
                <Wire UId="32">
                  <NameCon UId="27" Name="qKMR" />
                  <IdentCon UId="25" />
                </Wire>
                <Wire UId="33">
                  <NameCon UId="27" Name="qKSW" />
                  <IdentCon UId="26" />
                </Wire>
              </Wires>
            </FlgNet>
          </NetworkSource>
          <ProgrammingLanguage>FBD</ProgrammingLanguage>
        </AttributeList>
        <ObjectList>
          <MultilingualText ID="13" CompositionName="Comment">
            <ObjectList>
              <MultilingualTextItem ID="14" CompositionName="Items">
                <AttributeList>
                  <Culture>en-US</Culture>
                  <Text />
                </AttributeList>
              </MultilingualTextItem>
              <MultilingualTextItem ID="15" CompositionName="Items">
                <AttributeList>
                  <Culture>de-DE</Culture>
                  <Text />
                </AttributeList>
              </MultilingualTextItem>
            </ObjectList>
          </MultilingualText>
          <MultilingualText ID="16" CompositionName="Title">
            <ObjectList>
              <MultilingualTextItem ID="17" CompositionName="Items">
                <AttributeList>
                  <Culture>en-US</Culture>
                  <Text>Setpoint: dP,dR for the re-melting phase (classic)</Text>
                </AttributeList>
              </MultilingualTextItem>
              <MultilingualTextItem ID="18" CompositionName="Items">
                <AttributeList>
                  <Culture>de-DE</Culture>
                  <Text />
                </AttributeList>
              </MultilingualTextItem>
            </ObjectList>
          </MultilingualText>
        </ObjectList>
      </SW.Blocks.CompileUnit>
      <SW.Blocks.CompileUnit ID="19" CompositionName="CompileUnits">
        <AttributeList>
          <NetworkSource>
            <FlgNet xmlns="http://www.siemens.com/automation/Openness/SW/NetworkSource/FlgNet/v3">
              <Parts>
                <Access Scope="GlobalVariable" UId="21">
                  <Symbol>
                    <Component Name="MELT_PAR_DB" />
                    <Component Name="mr_cont_sel" />
                  </Symbol>
                </Access>
                <Access Scope="GlobalVariable" UId="22">
                  <Symbol>
                    <Component Name="MELT_CONT_DB" />
                    <Component Name="mr_out" />
                  </Symbol>
                </Access>
                <Access Scope="LocalVariable" UId="23">
                  <Symbol>
                    <Component Name="tPwrAdd" />
                  </Symbol>
                </Access>
                <Access Scope="GlobalVariable" UId="24">
                  <Symbol>
                    <Component Name="MELT_CONT_DB" />
                    <Component Name="sw_out" />
                  </Symbol>
                </Access>
                <Access Scope="LocalVariable" UId="25">
                  <Symbol>
                    <Component Name="tResAdd" />
                  </Symbol>
                </Access>
                <Part Name="Move" UId="26" DisabledENO="true">
                  <TemplateValue Name="Card" Type="Cardinality">1</TemplateValue>
                </Part>
                <Part Name="Move" UId="27" DisabledENO="true">
                  <TemplateValue Name="Card" Type="Cardinality">1</TemplateValue>
                </Part>
              </Parts>
              <Wires>
                <Wire UId="28">
                  <IdentCon UId="21" />
                  <NameCon UId="26" Name="en" />
                </Wire>
                <Wire UId="29">
                  <IdentCon UId="22" />
                  <NameCon UId="26" Name="in" />
                </Wire>
                <Wire UId="30">
                  <NameCon UId="26" Name="out1" />
                  <IdentCon UId="23" />
                </Wire>
                <Wire UId="31">
                  <NameCon UId="26" Name="eno" />
                  <NameCon UId="27" Name="en" />
                </Wire>
                <Wire UId="32">
                  <IdentCon UId="24" />
                  <NameCon UId="27" Name="in" />
                </Wire>
                <Wire UId="33">
                  <NameCon UId="27" Name="out1" />
                  <IdentCon UId="25" />
                </Wire>
              </Wires>
            </FlgNet>
          </NetworkSource>
          <ProgrammingLanguage>FBD</ProgrammingLanguage>
        </AttributeList>
        <ObjectList>
          <MultilingualText ID="1A" CompositionName="Comment">
            <ObjectList>
              <MultilingualTextItem ID="1B" CompositionName="Items">
                <AttributeList>
                  <Culture>en-US</Culture>
                  <Text>If the MR-, Sw-controllers will configured for the physical units, we can use more simple calculation for P, R.
The output configuration for MR-cont can be power [kW], or a power changing [kW/min]
The output configuration for Sw-cont can be resistance [mOhm], or a resistance changing [mOhm/min]

A new bonus is smooth process regulation.</Text>
                </AttributeList>
              </MultilingualTextItem>
              <MultilingualTextItem ID="1C" CompositionName="Items">
                <AttributeList>
                  <Culture>de-DE</Culture>
                  <Text />
                </AttributeList>
              </MultilingualTextItem>
            </ObjectList>
          </MultilingualText>
          <MultilingualText ID="1D" CompositionName="Title">
            <ObjectList>
              <MultilingualTextItem ID="1E" CompositionName="Items">
                <AttributeList>
                  <Culture>en-US</Culture>
                  <Text>Setpoint: dP,dR for the re-melting phase (new)</Text>
                </AttributeList>
              </MultilingualTextItem>
              <MultilingualTextItem ID="1F" CompositionName="Items">
                <AttributeList>
                  <Culture>de-DE</Culture>
                  <Text />
                </AttributeList>
              </MultilingualTextItem>
            </ObjectList>
          </MultilingualText>
        </ObjectList>
      </SW.Blocks.CompileUnit>
      <SW.Blocks.CompileUnit ID="20" CompositionName="CompileUnits">
        <AttributeList>
          <NetworkSource>
            <FlgNet xmlns="http://www.siemens.com/automation/Openness/SW/NetworkSource/FlgNet/v3">
              <Parts>
                <Access Scope="LocalVariable" UId="21">
                  <Symbol>
                    <Component Name="tPwrAdd" />
                  </Symbol>
                </Access>
                <Access Scope="GlobalVariable" UId="22">
                  <Symbol>
                    <Component Name="MELT_VAR" />
                    <Component Name="cont_dP" />
                  </Symbol>
                </Access>
                <Access Scope="LocalVariable" UId="23">
                  <Symbol>
                    <Component Name="tResAdd" />
                  </Symbol>
                </Access>
                <Access Scope="GlobalVariable" UId="24">
                  <Symbol>
                    <Component Name="MELT_VAR" />
                    <Component Name="cont_dR" />
                  </Symbol>
                </Access>
                <Part Name="Move" UId="25" DisabledENO="true">
                  <TemplateValue Name="Card" Type="Cardinality">1</TemplateValue>
                </Part>
                <Part Name="Move" UId="26" DisabledENO="true">
                  <TemplateValue Name="Card" Type="Cardinality">1</TemplateValue>
                </Part>
              </Parts>
              <Wires>
                <Wire UId="29">
                  <OpenCon UId="27" />
                  <NameCon UId="25" Name="en" />
                </Wire>
                <Wire UId="30">
                  <IdentCon UId="21" />
                  <NameCon UId="25" Name="in" />
                </Wire>
                <Wire UId="31">
                  <NameCon UId="25" Name="out1" />
                  <IdentCon UId="22" />
                </Wire>
                <Wire UId="32">
                  <OpenCon UId="28" />
                  <NameCon UId="26" Name="en" />
                </Wire>
                <Wire UId="33">
                  <IdentCon UId="23" />
                  <NameCon UId="26" Name="in" />
                </Wire>
                <Wire UId="34">
                  <NameCon UId="26" Name="out1" />
                  <IdentCon UId="24" />
                </Wire>
              </Wires>
            </FlgNet>
          </NetworkSource>
          <ProgrammingLanguage>FBD</ProgrammingLanguage>
        </AttributeList>
        <ObjectList>
          <MultilingualText ID="21" CompositionName="Comment">
            <ObjectList>
              <MultilingualTextItem ID="22" CompositionName="Items">
                <AttributeList>
                  <Culture>en-US</Culture>
                  <Text />
                </AttributeList>
              </MultilingualTextItem>
              <MultilingualTextItem ID="23" CompositionName="Items">
                <AttributeList>
                  <Culture>de-DE</Culture>
                  <Text />
                </AttributeList>
              </MultilingualTextItem>
            </ObjectList>
          </MultilingualText>
          <MultilingualText ID="24" CompositionName="Title">
            <ObjectList>
              <MultilingualTextItem ID="25" CompositionName="Items">
                <AttributeList>
                  <Culture>en-US</Culture>
                  <Text>dP, dR out</Text>
                </AttributeList>
              </MultilingualTextItem>
              <MultilingualTextItem ID="26" CompositionName="Items">
                <AttributeList>
                  <Culture>de-DE</Culture>
                  <Text />
                </AttributeList>
              </MultilingualTextItem>
            </ObjectList>
          </MultilingualText>
        </ObjectList>
      </SW.Blocks.CompileUnit>
      <SW.Blocks.CompileUnit ID="27" CompositionName="CompileUnits">
        <AttributeList>
          <NetworkSource>
            <FlgNet xmlns="http://www.siemens.com/automation/Openness/SW/NetworkSource/FlgNet/v3">
              <Parts>
                <Access Scope="GlobalVariable" UId="21">
                  <Symbol>
                    <Component Name="MELT_BOOL_DB" />
                    <Component Name="melt_main_phase" />
                  </Symbol>
                </Access>
                <Access Scope="GlobalVariable" UId="22">
                  <Symbol>
                    <Component Name="MELT_CONT_DB" />
                    <Component Name="res_set" />
                  </Symbol>
                </Access>
                <Access Scope="GlobalVariable" UId="23">
                  <Symbol>
                    <Component Name="MELT_VAR" />
                    <Component Name="curve_HT_R_start" />
                  </Symbol>
                </Access>
                <Access Scope="GlobalVariable" UId="24">
                  <Symbol>
                    <Component Name="MELT_CONT_DB" />
                    <Component Name="pwr_set" />
                  </Symbol>
                </Access>
                <Access Scope="GlobalVariable" UId="25">
                  <Symbol>
                    <Component Name="MELT_VAR" />
                    <Component Name="curve_HT_P_start" />
                  </Symbol>
                </Access>
                <Part Name="A" UId="26">
                  <TemplateValue Name="Card" Type="Cardinality">1</TemplateValue>
                </Part>
                <Part Name="Move" UId="27" DisabledENO="false">
                  <TemplateValue Name="Card" Type="Cardinality">1</TemplateValue>
                </Part>
                <Part Name="Move" UId="28" DisabledENO="false">
                  <TemplateValue Name="Card" Type="Cardinality">1</TemplateValue>
                </Part>
              </Parts>
              <Wires>
                <Wire UId="29">
                  <IdentCon UId="21" />
                  <NameCon UId="26" Name="in1" />
                </Wire>
                <Wire UId="30">
                  <NameCon UId="26" Name="out" />
                  <NameCon UId="27" Name="en" />
                  <NameCon UId="28" Name="en" />
                </Wire>
                <Wire UId="31">
                  <IdentCon UId="22" />
                  <NameCon UId="27" Name="in" />
                </Wire>
                <Wire UId="32">
                  <NameCon UId="27" Name="out1" />
                  <IdentCon UId="23" />
                </Wire>
                <Wire UId="33">
                  <IdentCon UId="24" />
                  <NameCon UId="28" Name="in" />
                </Wire>
                <Wire UId="34">
                  <NameCon UId="28" Name="out1" />
                  <IdentCon UId="25" />
                </Wire>
              </Wires>
            </FlgNet>
          </NetworkSource>
          <ProgrammingLanguage>FBD</ProgrammingLanguage>
        </AttributeList>
        <ObjectList>
          <MultilingualText ID="28" CompositionName="Comment">
            <ObjectList>
              <MultilingualTextItem ID="29" CompositionName="Items">
                <AttributeList>
                  <Culture>en-US</Culture>
                  <Text />
                </AttributeList>
              </MultilingualTextItem>
              <MultilingualTextItem ID="2A" CompositionName="Items">
                <AttributeList>
                  <Culture>de-DE</Culture>
                  <Text />
                </AttributeList>
              </MultilingualTextItem>
            </ObjectList>
          </MultilingualText>
          <MultilingualText ID="2B" CompositionName="Title">
            <ObjectList>
              <MultilingualTextItem ID="2C" CompositionName="Items">
                <AttributeList>
                  <Culture>en-US</Culture>
                  <Text>Prepare starting point for HT-phase setpoints</Text>
                </AttributeList>
              </MultilingualTextItem>
              <MultilingualTextItem ID="2D" CompositionName="Items">
                <AttributeList>
                  <Culture>de-DE</Culture>
                  <Text />
                </AttributeList>
              </MultilingualTextItem>
            </ObjectList>
          </MultilingualText>
        </ObjectList>
      </SW.Blocks.CompileUnit>
      <SW.Blocks.CompileUnit ID="2E" CompositionName="CompileUnits">
        <AttributeList>
          <NetworkSource>
            <FlgNet xmlns="http://www.siemens.com/automation/Openness/SW/NetworkSource/FlgNet/v3">
              <Parts>
                <Access Scope="GlobalVariable" UId="21">
                  <Symbol>
                    <Component Name="MELT_BOOL_DB" />
                    <Component Name="melt_ht_phase" />
                  </Symbol>
                </Access>
                <Access Scope="GlobalVariable" UId="22">
                  <Symbol>
                    <Component Name="MELT_VAR" />
                    <Component Name="curve_HT_PR_out" />
                  </Symbol>
                </Access>
                <Access Scope="GlobalVariable" UId="23">
                  <Symbol>
                    <Component Name="MELT_VAR" />
                    <Component Name="curve_HT_R_out" />
                  </Symbol>
                </Access>
                <Access Scope="GlobalVariable" UId="24">
                  <Symbol>
                    <Component Name="MELT_VAR" />
                    <Component Name="curve_HT_R_start" />
                  </Symbol>
                </Access>
                <Access Scope="GlobalVariable" UId="25">
                  <Symbol>
                    <Component Name="MELT_VAR" />
                    <Component Name="curve_HT_P_start" />
                  </Symbol>
                </Access>
                <Access Scope="LocalVariable" UId="26">
                  <Symbol>
                    <Component Name="tHTResistance" />
                  </Symbol>
                </Access>
                <Access Scope="LocalVariable" UId="27">
                  <Symbol>
                    <Component Name="tHTPower" />
                  </Symbol>
                </Access>
                <Call UId="28">
                  <CallInfo Name="MELT_HT_SET_PR" BlockType="FC">
                    <Parameter Name="iEnable" Section="Input" Type="Bool" />
                    <Parameter Name="iPwrRel" Section="Input" Type="Real" />
                    <Parameter Name="iResRel" Section="Input" Type="Real" />
                    <Parameter Name="iStartP" Section="Input" Type="Real" />
                    <Parameter Name="iStartR" Section="Input" Type="Real" />
                    <Parameter Name="qR" Section="Output" Type="Real" />
                    <Parameter Name="qP" Section="Output" Type="Real" />
                  </CallInfo>
                </Call>
              </Parts>
              <Wires>
                <Wire UId="30">
                  <OpenCon UId="29" />
                  <NameCon UId="28" Name="en" />
                </Wire>
                <Wire UId="31">
                  <IdentCon UId="21" />
                  <NameCon UId="28" Name="iEnable" />
                </Wire>
                <Wire UId="32">
                  <IdentCon UId="22" />
                  <NameCon UId="28" Name="iPwrRel" />
                </Wire>
                <Wire UId="33">
                  <IdentCon UId="23" />
                  <NameCon UId="28" Name="iResRel" />
                </Wire>
                <Wire UId="34">
                  <IdentCon UId="24" />
                  <NameCon UId="28" Name="iStartP" />
                </Wire>
                <Wire UId="35">
                  <IdentCon UId="25" />
                  <NameCon UId="28" Name="iStartR" />
                </Wire>
                <Wire UId="36">
                  <NameCon UId="28" Name="qR" />
                  <IdentCon UId="26" />
                </Wire>
                <Wire UId="37">
                  <NameCon UId="28" Name="qP" />
                  <IdentCon UId="27" />
                </Wire>
              </Wires>
            </FlgNet>
          </NetworkSource>
          <ProgrammingLanguage>FBD</ProgrammingLanguage>
        </AttributeList>
        <ObjectList>
          <MultilingualText ID="2F" CompositionName="Comment">
            <ObjectList>
              <MultilingualTextItem ID="30" CompositionName="Items">
                <AttributeList>
                  <Culture>en-US</Culture>
                  <Text />
                </AttributeList>
              </MultilingualTextItem>
              <MultilingualTextItem ID="31" CompositionName="Items">
                <AttributeList>
                  <Culture>de-DE</Culture>
                  <Text />
                </AttributeList>
              </MultilingualTextItem>
            </ObjectList>
          </MultilingualText>
          <MultilingualText ID="32" CompositionName="Title">
            <ObjectList>
              <MultilingualTextItem ID="33" CompositionName="Items">
                <AttributeList>
                  <Culture>en-US</Culture>
                  <Text>Setpoint: P,R for the hottopping phase</Text>
                </AttributeList>
              </MultilingualTextItem>
              <MultilingualTextItem ID="34" CompositionName="Items">
                <AttributeList>
                  <Culture>de-DE</Culture>
                  <Text />
                </AttributeList>
              </MultilingualTextItem>
            </ObjectList>
          </MultilingualText>
        </ObjectList>
      </SW.Blocks.CompileUnit>
      <SW.Blocks.CompileUnit ID="35" CompositionName="CompileUnits">
        <AttributeList>
          <NetworkSource>
            <FlgNet xmlns="http://www.siemens.com/automation/Openness/SW/NetworkSource/FlgNet/v3">
              <Parts>
                <Access Scope="GlobalVariable" UId="21">
                  <Symbol>
                    <Component Name="MELT_BOOL_DB" />
                    <Component Name="melt_start_phase" />
                  </Symbol>
                </Access>
                <Access Scope="GlobalVariable" UId="22">
                  <Symbol>
                    <Component Name="MELT_BOOL_DB" />
                    <Component Name="melting" />
                  </Symbol>
                </Access>
                <Access Scope="LocalVariable" UId="23">
                  <Symbol>
                    <Component Name="tUseST" />
                  </Symbol>
                </Access>
                <Access Scope="GlobalVariable" UId="24">
                  <Symbol>
                    <Component Name="MELT_BOOL_DB" />
                    <Component Name="melt_ht_phase" />
                  </Symbol>
                </Access>
                <Access Scope="LocalVariable" UId="25">
                  <Symbol>
                    <Component Name="tUseHT" />
                  </Symbol>
                </Access>
                <Access Scope="GlobalVariable" UId="26">
                  <Symbol>
                    <Component Name="MELT_PWR_DB" />
                    <Component Name="OCT" />
                    <Component Name="Run" />
                  </Symbol>
                </Access>
                <Access Scope="GlobalVariable" UId="27">
                  <Symbol>
                    <Component Name="MELT_BOOL_DB" />
                    <Component Name="melting" />
                  </Symbol>
                </Access>
                <Access Scope="LocalVariable" UId="28">
                  <Symbol>
                    <Component Name="tUseForOCT" />
                  </Symbol>
                </Access>
                <Part Name="O" UId="29">
                  <TemplateValue Name="Card" Type="Cardinality">2</TemplateValue>
                  <Negated Name="in2" />
                </Part>
                <Part Name="Coil" UId="30" />
                <Part Name="Coil" UId="31" />
                <Part Name="A" UId="32">
                  <TemplateValue Name="Card" Type="Cardinality">2</TemplateValue>
                  <Negated Name="in2" />
                </Part>
                <Part Name="Coil" UId="33" />
              </Parts>
              <Wires>
                <Wire UId="34">
                  <IdentCon UId="21" />
                  <NameCon UId="29" Name="in1" />
                </Wire>
                <Wire UId="35">
                  <IdentCon UId="22" />
                  <NameCon UId="29" Name="in2" />
                </Wire>
                <Wire UId="36">
                  <NameCon UId="29" Name="out" />
                  <NameCon UId="30" Name="in" />
                </Wire>
                <Wire UId="37">
                  <IdentCon UId="23" />
                  <NameCon UId="30" Name="operand" />
                </Wire>
                <Wire UId="38">
                  <IdentCon UId="24" />
                  <NameCon UId="31" Name="in" />
                </Wire>
                <Wire UId="39">
                  <IdentCon UId="25" />
                  <NameCon UId="31" Name="operand" />
                </Wire>
                <Wire UId="40">
                  <IdentCon UId="26" />
                  <NameCon UId="32" Name="in1" />
                </Wire>
                <Wire UId="41">
                  <IdentCon UId="27" />
                  <NameCon UId="32" Name="in2" />
                </Wire>
                <Wire UId="42">
                  <NameCon UId="32" Name="out" />
                  <NameCon UId="33" Name="in" />
                </Wire>
                <Wire UId="43">
                  <IdentCon UId="28" />
                  <NameCon UId="33" Name="operand" />
                </Wire>
              </Wires>
            </FlgNet>
          </NetworkSource>
          <ProgrammingLanguage>FBD</ProgrammingLanguage>
        </AttributeList>
        <ObjectList>
          <MultilingualText ID="36" CompositionName="Comment">
            <ObjectList>
              <MultilingualTextItem ID="37" CompositionName="Items">
                <AttributeList>
                  <Culture>en-US</Culture>
                  <Text />
                </AttributeList>
              </MultilingualTextItem>
              <MultilingualTextItem ID="38" CompositionName="Items">
                <AttributeList>
                  <Culture>de-DE</Culture>
                  <Text />
                </AttributeList>
              </MultilingualTextItem>
            </ObjectList>
          </MultilingualText>
          <MultilingualText ID="39" CompositionName="Title">
            <ObjectList>
              <MultilingualTextItem ID="3A" CompositionName="Items">
                <AttributeList>
                  <Culture>en-US</Culture>
                  <Text>Setpoint selectors flags</Text>
                </AttributeList>
              </MultilingualTextItem>
              <MultilingualTextItem ID="3B" CompositionName="Items">
                <AttributeList>
                  <Culture>de-DE</Culture>
                  <Text />
                </AttributeList>
              </MultilingualTextItem>
            </ObjectList>
          </MultilingualText>
        </ObjectList>
      </SW.Blocks.CompileUnit>
      <SW.Blocks.CompileUnit ID="3C" CompositionName="CompileUnits">
        <AttributeList>
          <NetworkSource>
            <FlgNet xmlns="http://www.siemens.com/automation/Openness/SW/NetworkSource/FlgNet/v3">
              <Parts>
                <Access Scope="GlobalVariable" UId="21">
                  <Symbol>
                    <Component Name="MELT_CONT_DB" />
                    <Component Name="pwr_cont_type" />
                  </Symbol>
                </Access>
                <Access Scope="GlobalVariable" UId="22">
                  <Symbol>
                    <Component Name="MELT_CONT_DB" />
                    <Component Name="pwr_act" />
                  </Symbol>
                </Access>
                <Access Scope="LocalVariable" UId="23">
                  <Symbol>
                    <Component Name="tPset_ST" />
                  </Symbol>
                </Access>
                <Access Scope="GlobalVariable" UId="24">
                  <Symbol>
                    <Component Name="MELT_VAR" />
                    <Component Name="curve_ST_P_out" />
                  </Symbol>
                </Access>
                <Access Scope="LocalVariable" UId="25">
                  <Symbol>
                    <Component Name="tPset_ST" />
                  </Symbol>
                </Access>
                <Part Name="A" UId="26">
                  <TemplateValue Name="Card" Type="Cardinality">1</TemplateValue>
                </Part>
                <Part Name="Move" UId="27" DisabledENO="true">
                  <TemplateValue Name="Card" Type="Cardinality">1</TemplateValue>
                  <Negated Name="eno" />
                </Part>
                <Part Name="Move" UId="28" DisabledENO="true">
                  <TemplateValue Name="Card" Type="Cardinality">1</TemplateValue>
                </Part>
              </Parts>
              <Wires>
                <Wire UId="29">
                  <IdentCon UId="21" />
                  <NameCon UId="26" Name="in1" />
                </Wire>
                <Wire UId="30">
                  <NameCon UId="26" Name="out" />
                  <NameCon UId="27" Name="en" />
                </Wire>
                <Wire UId="31">
                  <IdentCon UId="22" />
                  <NameCon UId="27" Name="in" />
                </Wire>
                <Wire UId="32">
                  <NameCon UId="27" Name="out1" />
                  <IdentCon UId="23" />
                </Wire>
                <Wire UId="33">
                  <NameCon UId="27" Name="eno" />
                  <NameCon UId="28" Name="en" />
                </Wire>
                <Wire UId="34">
                  <IdentCon UId="24" />
                  <NameCon UId="28" Name="in" />
                </Wire>
                <Wire UId="35">
                  <NameCon UId="28" Name="out1" />
                  <IdentCon UId="25" />
                </Wire>
              </Wires>
            </FlgNet>
          </NetworkSource>
          <ProgrammingLanguage>FBD</ProgrammingLanguage>
        </AttributeList>
        <ObjectList>
          <MultilingualText ID="3D" CompositionName="Comment">
            <ObjectList>
              <MultilingualTextItem ID="3E" CompositionName="Items">
                <AttributeList>
                  <Culture>en-US</Culture>
                  <Text>NB A problem can happen if P_act = 0 (CB is OFF, electrode is out)</Text>
                </AttributeList>
              </MultilingualTextItem>
              <MultilingualTextItem ID="3F" CompositionName="Items">
                <AttributeList>
                  <Culture>de-DE</Culture>
                  <Text />
                </AttributeList>
              </MultilingualTextItem>
            </ObjectList>
          </MultilingualText>
          <MultilingualText ID="40" CompositionName="Title">
            <ObjectList>
              <MultilingualTextItem ID="41" CompositionName="Items">
                <AttributeList>
                  <Culture>en-US</Culture>
                  <Text>Select power for starting curve </Text>
                </AttributeList>
              </MultilingualTextItem>
              <MultilingualTextItem ID="42" CompositionName="Items">
                <AttributeList>
                  <Culture>de-DE</Culture>
                  <Text />
                </AttributeList>
              </MultilingualTextItem>
            </ObjectList>
          </MultilingualText>
        </ObjectList>
      </SW.Blocks.CompileUnit>
      <SW.Blocks.CompileUnit ID="43" CompositionName="CompileUnits">
        <AttributeList>
          <NetworkSource>
            <FlgNet xmlns="http://www.siemens.com/automation/Openness/SW/NetworkSource/FlgNet/v3">
              <Parts>
                <Access Scope="LocalVariable" UId="21">
                  <Symbol>
                    <Component Name="tUseST" />
                  </Symbol>
                </Access>
                <Access Scope="LocalVariable" UId="22">
                  <Symbol>
                    <Component Name="tUseForOCT" />
                  </Symbol>
                </Access>
                <Access Scope="LocalVariable" UId="23">
                  <Symbol>
                    <Component Name="tUseHT" />
                  </Symbol>
                </Access>
                <Access Scope="GlobalVariable" UId="24">
                  <Symbol>
                    <Component Name="MELT_BOOL_DB" />
                    <Component Name="melt_main_phase" />
                  </Symbol>
                </Access>
                <Access Scope="GlobalVariable" UId="25">
                  <Symbol>
                    <Component Name="MELT_CONT_DB" />
                    <Component Name="mr_is_on" />
                  </Symbol>
                </Access>
                <Access Scope="LocalVariable" UId="26">
                  <Symbol>
                    <Component Name="tCalcMR" />
                  </Symbol>
                </Access>
                <Access Scope="GlobalVariable" UId="27">
                  <Symbol>
                    <Component Name="MELT_PAR_DB" />
                    <Component Name="mr_cont_sel" />
                  </Symbol>
                </Access>
                <Access Scope="LocalVariable" UId="28">
                  <Symbol>
                    <Component Name="tPset_ST" />
                  </Symbol>
                </Access>
                <Access Scope="GlobalVariable" UId="29">
                  <Symbol>
                    <Component Name="MELT_VAR" />
                    <Component Name="ST_P" />
                    <Component Name="y" AccessModifier="Array">
                      <Access Scope="LiteralConstant">
                        <Constant>
                          <ConstantType>DInt</ConstantType>
                          <ConstantValue>1</ConstantValue>
                        </Constant>
                      </Access>
                    </Component>
                  </Symbol>
                </Access>
                <Access Scope="LocalVariable" UId="30">
                  <Symbol>
                    <Component Name="tHTPower" />
                  </Symbol>
                </Access>
                <Access Scope="LocalVariable" UId="31">
                  <Symbol>
                    <Component Name="tPwrAdd" />
                  </Symbol>
                </Access>
                <Access Scope="GlobalVariable" UId="32">
                  <Symbol>
                    <Component Name="MELT_CONT_DB" />
                    <Component Name="pwr_set" />
                  </Symbol>
                </Access>
                <Part Name="A" UId="33">
                  <TemplateValue Name="Card" Type="Cardinality">2</TemplateValue>
                </Part>
                <Call UId="34">
                  <CallInfo Name="SETPOINT_SEL" BlockType="FC">
                    <Parameter Name="iUseAbs1" Section="Input" Type="Bool" />
                    <Parameter Name="iUseAbs2" Section="Input" Type="Bool" />
                    <Parameter Name="iUseAbs3" Section="Input" Type="Bool" />
                    <Parameter Name="iUseRel" Section="Input" Type="Bool" />
                    <Parameter Name="iClockRel" Section="Input" Type="Bool" />
                    <Parameter Name="pRelMode" Section="Input" Type="Bool" />
                    <Parameter Name="iValue1" Section="Input" Type="Real" />
                    <Parameter Name="iValue2" Section="Input" Type="Real" />
                    <Parameter Name="iValue3" Section="Input" Type="Real" />
                    <Parameter Name="iValueR" Section="Input" Type="Real" />
                    <Parameter Name="ioValue" Section="InOut" Type="Real" />
                  </CallInfo>
                </Call>
              </Parts>
              <Wires>
                <Wire UId="36">
                  <IdentCon UId="24" />
                  <NameCon UId="33" Name="in1" />
                </Wire>
                <Wire UId="37">
                  <IdentCon UId="25" />
                  <NameCon UId="33" Name="in2" />
                </Wire>
                <Wire UId="38">
                  <NameCon UId="33" Name="out" />
                  <NameCon UId="34" Name="iUseRel" />
                </Wire>
                <Wire UId="39">
                  <OpenCon UId="35" />
                  <NameCon UId="34" Name="en" />
                </Wire>
                <Wire UId="40">
                  <IdentCon UId="21" />
                  <NameCon UId="34" Name="iUseAbs1" />
                </Wire>
                <Wire UId="41">
                  <IdentCon UId="22" />
                  <NameCon UId="34" Name="iUseAbs2" />
                </Wire>
                <Wire UId="42">
                  <IdentCon UId="23" />
                  <NameCon UId="34" Name="iUseAbs3" />
                </Wire>
                <Wire UId="43">
                  <IdentCon UId="26" />
                  <NameCon UId="34" Name="iClockRel" />
                </Wire>
                <Wire UId="44">
                  <IdentCon UId="27" />
                  <NameCon UId="34" Name="pRelMode" />
                </Wire>
                <Wire UId="45">
                  <IdentCon UId="28" />
                  <NameCon UId="34" Name="iValue1" />
                </Wire>
                <Wire UId="46">
                  <IdentCon UId="29" />
                  <NameCon UId="34" Name="iValue2" />
                </Wire>
                <Wire UId="47">
                  <IdentCon UId="30" />
                  <NameCon UId="34" Name="iValue3" />
                </Wire>
                <Wire UId="48">
                  <IdentCon UId="31" />
                  <NameCon UId="34" Name="iValueR" />
                </Wire>
                <Wire UId="49">
                  <IdentCon UId="32" />
                  <NameCon UId="34" Name="ioValue" />
                </Wire>
              </Wires>
            </FlgNet>
          </NetworkSource>
          <ProgrammingLanguage>FBD</ProgrammingLanguage>
        </AttributeList>
        <ObjectList>
          <MultilingualText ID="44" CompositionName="Comment">
            <ObjectList>
              <MultilingualTextItem ID="45" CompositionName="Items">
                <AttributeList>
                  <Culture>en-US</Culture>
                  <Text />
                </AttributeList>
              </MultilingualTextItem>
              <MultilingualTextItem ID="46" CompositionName="Items">
                <AttributeList>
                  <Culture>de-DE</Culture>
                  <Text />
                </AttributeList>
              </MultilingualTextItem>
            </ObjectList>
          </MultilingualText>
          <MultilingualText ID="47" CompositionName="Title">
            <ObjectList>
              <MultilingualTextItem ID="48" CompositionName="Items">
                <AttributeList>
                  <Culture>en-US</Culture>
                  <Text>Setpoint: POWER</Text>
                </AttributeList>
              </MultilingualTextItem>
              <MultilingualTextItem ID="49" CompositionName="Items">
                <AttributeList>
                  <Culture>de-DE</Culture>
                  <Text />
                </AttributeList>
              </MultilingualTextItem>
            </ObjectList>
          </MultilingualText>
        </ObjectList>
      </SW.Blocks.CompileUnit>
      <SW.Blocks.CompileUnit ID="4A" CompositionName="CompileUnits">
        <AttributeList>
          <NetworkSource>
            <FlgNet xmlns="http://www.siemens.com/automation/Openness/SW/NetworkSource/FlgNet/v3">
              <Parts>
                <Access Scope="LiteralConstant" UId="21">
                  <Constant>
                    <ConstantType>Real</ConstantType>
                    <ConstantValue>200.0</ConstantValue>
                  </Constant>
                </Access>
                <Access Scope="GlobalVariable" UId="22">
                  <Symbol>
                    <Component Name="MELT_CONT_DB" />
                    <Component Name="pwr_set" />
                  </Symbol>
                </Access>
                <Access Scope="LiteralConstant" UId="23">
                  <Constant>
                    <ConstantType>Real</ConstantType>
                    <ConstantValue>1750.0</ConstantValue>
                  </Constant>
                </Access>
                <Access Scope="GlobalVariable" UId="24">
                  <Symbol>
                    <Component Name="MELT_CONT_DB" />
                    <Component Name="pwr_set" />
                  </Symbol>
                </Access>
                <Part Name="LIMIT" Version="1.0" UId="25" DisabledENO="true">
                  <TemplateValue Name="value_type" Type="Type">Real</TemplateValue>
                </Part>
              </Parts>
              <Wires>
                <Wire UId="27">
                  <OpenCon UId="26" />
                  <NameCon UId="25" Name="en" />
                </Wire>
                <Wire UId="28">
                  <IdentCon UId="21" />
                  <NameCon UId="25" Name="MN" />
                </Wire>
                <Wire UId="29">
                  <IdentCon UId="22" />
                  <NameCon UId="25" Name="IN" />
                </Wire>
                <Wire UId="30">
                  <IdentCon UId="23" />
                  <NameCon UId="25" Name="MX" />
                </Wire>
                <Wire UId="31">
                  <NameCon UId="25" Name="OUT" />
                  <IdentCon UId="24" />
                </Wire>
              </Wires>
            </FlgNet>
          </NetworkSource>
          <ProgrammingLanguage>FBD</ProgrammingLanguage>
        </AttributeList>
        <ObjectList>
          <MultilingualText ID="4B" CompositionName="Comment">
            <ObjectList>
              <MultilingualTextItem ID="4C" CompositionName="Items">
                <AttributeList>
                  <Culture>en-US</Culture>
                  <Text>2.000000e+002</Text>
                </AttributeList>
              </MultilingualTextItem>
              <MultilingualTextItem ID="4D" CompositionName="Items">
                <AttributeList>
                  <Culture>de-DE</Culture>
                  <Text />
                </AttributeList>
              </MultilingualTextItem>
            </ObjectList>
          </MultilingualText>
          <MultilingualText ID="4E" CompositionName="Title">
            <ObjectList>
              <MultilingualTextItem ID="4F" CompositionName="Items">
                <AttributeList>
                  <Culture>en-US</Culture>
                  <Text>Setpoint: POWER limit</Text>
                </AttributeList>
              </MultilingualTextItem>
              <MultilingualTextItem ID="50" CompositionName="Items">
                <AttributeList>
                  <Culture>de-DE</Culture>
                  <Text />
                </AttributeList>
              </MultilingualTextItem>
            </ObjectList>
          </MultilingualText>
        </ObjectList>
      </SW.Blocks.CompileUnit>
      <SW.Blocks.CompileUnit ID="51" CompositionName="CompileUnits">
        <AttributeList>
          <NetworkSource>
            <FlgNet xmlns="http://www.siemens.com/automation/Openness/SW/NetworkSource/FlgNet/v3">
              <Parts>
                <Access Scope="GlobalVariable" UId="21">
                  <Symbol>
                    <Component Name="MELT_CONT_DB" />
                    <Component Name="pwr_mode" />
                  </Symbol>
                </Access>
                <Access Scope="GlobalVariable" UId="22">
                  <Symbol>
                    <Component Name="MELT_VAR" />
                    <Component Name="curve_ST_U_out" />
                  </Symbol>
                </Access>
                <Access Scope="GlobalVariable" UId="23">
                  <Symbol>
                    <Component Name="MELT_CONT_DB" />
                    <Component Name="pwr_dir" />
                  </Symbol>
                </Access>
                <Part Name="Move" UId="24" DisabledENO="true">
                  <TemplateValue Name="Card" Type="Cardinality">1</TemplateValue>
                </Part>
              </Parts>
              <Wires>
                <Wire UId="25">
                  <IdentCon UId="21" />
                  <NameCon UId="24" Name="en" />
                </Wire>
                <Wire UId="26">
                  <IdentCon UId="22" />
                  <NameCon UId="24" Name="in" />
                </Wire>
                <Wire UId="27">
                  <NameCon UId="24" Name="out1" />
                  <IdentCon UId="23" />
                </Wire>
              </Wires>
            </FlgNet>
          </NetworkSource>
          <ProgrammingLanguage>FBD</ProgrammingLanguage>
        </AttributeList>
        <ObjectList>
          <MultilingualText ID="52" CompositionName="Comment">
            <ObjectList>
              <MultilingualTextItem ID="53" CompositionName="Items">
                <AttributeList>
                  <Culture>en-US</Culture>
                  <Text />
                </AttributeList>
              </MultilingualTextItem>
              <MultilingualTextItem ID="54" CompositionName="Items">
                <AttributeList>
                  <Culture>de-DE</Culture>
                  <Text />
                </AttributeList>
              </MultilingualTextItem>
            </ObjectList>
          </MultilingualText>
          <MultilingualText ID="55" CompositionName="Title">
            <ObjectList>
              <MultilingualTextItem ID="56" CompositionName="Items">
                <AttributeList>
                  <Culture>en-US</Culture>
                  <Text>Setpoint: VOLTAGE</Text>
                </AttributeList>
              </MultilingualTextItem>
              <MultilingualTextItem ID="57" CompositionName="Items">
                <AttributeList>
                  <Culture>de-DE</Culture>
                  <Text />
                </AttributeList>
              </MultilingualTextItem>
            </ObjectList>
          </MultilingualText>
        </ObjectList>
      </SW.Blocks.CompileUnit>
      <SW.Blocks.CompileUnit ID="58" CompositionName="CompileUnits">
        <AttributeList>
          <NetworkSource>
            <FlgNet xmlns="http://www.siemens.com/automation/Openness/SW/NetworkSource/FlgNet/v3">
              <Parts>
                <Access Scope="LocalVariable" UId="21">
                  <Symbol>
                    <Component Name="tUseST" />
                  </Symbol>
                </Access>
                <Access Scope="LocalVariable" UId="22">
                  <Symbol>
                    <Component Name="tUseForOCT" />
                  </Symbol>
                </Access>
                <Access Scope="LocalVariable" UId="23">
                  <Symbol>
                    <Component Name="tUseHT" />
                  </Symbol>
                </Access>
                <Access Scope="GlobalVariable" UId="24">
                  <Symbol>
                    <Component Name="MELT_BOOL_DB" />
                    <Component Name="melt_main_phase" />
                  </Symbol>
                </Access>
                <Access Scope="GlobalVariable" UId="25">
                  <Symbol>
                    <Component Name="MELT_CONT_DB" />
                    <Component Name="sw_is_on" />
                  </Symbol>
                </Access>
                <Access Scope="LocalVariable" UId="26">
                  <Symbol>
                    <Component Name="tCalcSW" />
                  </Symbol>
                </Access>
                <Access Scope="LiteralConstant" UId="27">
                  <Constant>
                    <ConstantType>Bool</ConstantType>
                    <ConstantValue>false</ConstantValue>
                  </Constant>
                </Access>
                <Access Scope="GlobalVariable" UId="28">
                  <Symbol>
                    <Component Name="MELT_VAR" />
                    <Component Name="curve_ST_R_out" />
                  </Symbol>
                </Access>
                <Access Scope="LiteralConstant" UId="29">
                  <Constant>
                    <ConstantType>Real</ConstantType>
                    <ConstantValue>12.5</ConstantValue>
                  </Constant>
                </Access>
                <Access Scope="LocalVariable" UId="30">
                  <Symbol>
                    <Component Name="tHTResistance" />
                  </Symbol>
                </Access>
                <Access Scope="LocalVariable" UId="31">
                  <Symbol>
                    <Component Name="tResAdd" />
                  </Symbol>
                </Access>
                <Access Scope="GlobalVariable" UId="32">
                  <Symbol>
                    <Component Name="MELT_CONT_DB" />
                    <Component Name="res_set" />
                  </Symbol>
                </Access>
                <Part Name="A" UId="33">
                  <TemplateValue Name="Card" Type="Cardinality">2</TemplateValue>
                </Part>
                <Call UId="34">
                  <CallInfo Name="SETPOINT_SEL" BlockType="FC">
                    <Parameter Name="iUseAbs1" Section="Input" Type="Bool" />
                    <Parameter Name="iUseAbs2" Section="Input" Type="Bool" />
                    <Parameter Name="iUseAbs3" Section="Input" Type="Bool" />
                    <Parameter Name="iUseRel" Section="Input" Type="Bool" />
                    <Parameter Name="iClockRel" Section="Input" Type="Bool" />
                    <Parameter Name="pRelMode" Section="Input" Type="Bool" />
                    <Parameter Name="iValue1" Section="Input" Type="Real" />
                    <Parameter Name="iValue2" Section="Input" Type="Real" />
                    <Parameter Name="iValue3" Section="Input" Type="Real" />
                    <Parameter Name="iValueR" Section="Input" Type="Real" />
                    <Parameter Name="ioValue" Section="InOut" Type="Real" />
                  </CallInfo>
                </Call>
              </Parts>
              <Wires>
                <Wire UId="36">
                  <IdentCon UId="24" />
                  <NameCon UId="33" Name="in1" />
                </Wire>
                <Wire UId="37">
                  <IdentCon UId="25" />
                  <NameCon UId="33" Name="in2" />
                </Wire>
                <Wire UId="38">
                  <NameCon UId="33" Name="out" />
                  <NameCon UId="34" Name="iUseRel" />
                </Wire>
                <Wire UId="39">
                  <OpenCon UId="35" />
                  <NameCon UId="34" Name="en" />
                </Wire>
                <Wire UId="40">
                  <IdentCon UId="21" />
                  <NameCon UId="34" Name="iUseAbs1" />
                </Wire>
                <Wire UId="41">
                  <IdentCon UId="22" />
                  <NameCon UId="34" Name="iUseAbs2" />
                </Wire>
                <Wire UId="42">
                  <IdentCon UId="23" />
                  <NameCon UId="34" Name="iUseAbs3" />
                </Wire>
                <Wire UId="43">
                  <IdentCon UId="26" />
                  <NameCon UId="34" Name="iClockRel" />
                </Wire>
                <Wire UId="44">
                  <IdentCon UId="27" />
                  <NameCon UId="34" Name="pRelMode" />
                </Wire>
                <Wire UId="45">
                  <IdentCon UId="28" />
                  <NameCon UId="34" Name="iValue1" />
                </Wire>
                <Wire UId="46">
                  <IdentCon UId="29" />
                  <NameCon UId="34" Name="iValue2" />
                </Wire>
                <Wire UId="47">
                  <IdentCon UId="30" />
                  <NameCon UId="34" Name="iValue3" />
                </Wire>
                <Wire UId="48">
                  <IdentCon UId="31" />
                  <NameCon UId="34" Name="iValueR" />
                </Wire>
                <Wire UId="49">
                  <IdentCon UId="32" />
                  <NameCon UId="34" Name="ioValue" />
                </Wire>
              </Wires>
            </FlgNet>
          </NetworkSource>
          <ProgrammingLanguage>FBD</ProgrammingLanguage>
        </AttributeList>
        <ObjectList>
          <MultilingualText ID="59" CompositionName="Comment">
            <ObjectList>
              <MultilingualTextItem ID="5A" CompositionName="Items">
                <AttributeList>
                  <Culture>en-US</Culture>
                  <Text>During OCT the cos(phi) is always 1, and this fact does a voltage calculation wrong.
To avoid this we will use special seed for resistance R!
R! = Rmin / cos_phi^2
For this plant cos_phi = 0.2 and Rmin = 0.5 mOhm
R! = 0.5 / 0,04 = 12,5 mOhm </Text>
                </AttributeList>
              </MultilingualTextItem>
              <MultilingualTextItem ID="5B" CompositionName="Items">
                <AttributeList>
                  <Culture>de-DE</Culture>
                  <Text />
                </AttributeList>
              </MultilingualTextItem>
            </ObjectList>
          </MultilingualText>
          <MultilingualText ID="5C" CompositionName="Title">
            <ObjectList>
              <MultilingualTextItem ID="5D" CompositionName="Items">
                <AttributeList>
                  <Culture>en-US</Culture>
                  <Text>Setpoint: RESISTANCE</Text>
                </AttributeList>
              </MultilingualTextItem>
              <MultilingualTextItem ID="5E" CompositionName="Items">
                <AttributeList>
                  <Culture>de-DE</Culture>
                  <Text />
                </AttributeList>
              </MultilingualTextItem>
            </ObjectList>
          </MultilingualText>
        </ObjectList>
      </SW.Blocks.CompileUnit>
      <SW.Blocks.CompileUnit ID="5F" CompositionName="CompileUnits">
        <AttributeList>
          <NetworkSource>
            <FlgNet xmlns="http://www.siemens.com/automation/Openness/SW/NetworkSource/FlgNet/v3">
              <Parts>
                <Access Scope="LiteralConstant" UId="21">
                  <Constant>
                    <ConstantType>Real</ConstantType>
                    <ConstantValue>1.0</ConstantValue>
                  </Constant>
                </Access>
                <Access Scope="GlobalVariable" UId="22">
                  <Symbol>
                    <Component Name="MELT_CONT_DB" />
                    <Component Name="res_set" />
                  </Symbol>
                </Access>
                <Access Scope="LiteralConstant" UId="23">
                  <Constant>
                    <ConstantType>Real</ConstantType>
                    <ConstantValue>7.5</ConstantValue>
                  </Constant>
                </Access>
                <Access Scope="GlobalVariable" UId="24">
                  <Symbol>
                    <Component Name="MELT_CONT_DB" />
                    <Component Name="res_set" />
                  </Symbol>
                </Access>
                <Part Name="LIMIT" Version="1.0" UId="25" DisabledENO="true">
                  <TemplateValue Name="value_type" Type="Type">Real</TemplateValue>
                </Part>
              </Parts>
              <Wires>
                <Wire UId="27">
                  <OpenCon UId="26" />
                  <NameCon UId="25" Name="en" />
                </Wire>
                <Wire UId="28">
                  <IdentCon UId="21" />
                  <NameCon UId="25" Name="MN" />
                </Wire>
                <Wire UId="29">
                  <IdentCon UId="22" />
                  <NameCon UId="25" Name="IN" />
                </Wire>
                <Wire UId="30">
                  <IdentCon UId="23" />
                  <NameCon UId="25" Name="MX" />
                </Wire>
                <Wire UId="31">
                  <NameCon UId="25" Name="OUT" />
                  <IdentCon UId="24" />
                </Wire>
              </Wires>
            </FlgNet>
          </NetworkSource>
          <ProgrammingLanguage>FBD</ProgrammingLanguage>
        </AttributeList>
        <ObjectList>
          <MultilingualText ID="60" CompositionName="Comment">
            <ObjectList>
              <MultilingualTextItem ID="61" CompositionName="Items">
                <AttributeList>
                  <Culture>en-US</Culture>
                  <Text>2.000000e+002</Text>
                </AttributeList>
              </MultilingualTextItem>
              <MultilingualTextItem ID="62" CompositionName="Items">
                <AttributeList>
                  <Culture>de-DE</Culture>
                  <Text />
                </AttributeList>
              </MultilingualTextItem>
            </ObjectList>
          </MultilingualText>
          <MultilingualText ID="63" CompositionName="Title">
            <ObjectList>
              <MultilingualTextItem ID="64" CompositionName="Items">
                <AttributeList>
                  <Culture>en-US</Culture>
                  <Text>Setpoint: RESISTANCE limit</Text>
                </AttributeList>
              </MultilingualTextItem>
              <MultilingualTextItem ID="65" CompositionName="Items">
                <AttributeList>
                  <Culture>de-DE</Culture>
                  <Text />
                </AttributeList>
              </MultilingualTextItem>
            </ObjectList>
          </MultilingualText>
        </ObjectList>
      </SW.Blocks.CompileUnit>
      <SW.Blocks.CompileUnit ID="66" CompositionName="CompileUnits">
        <AttributeList>
          <NetworkSource>
            <FlgNet xmlns="http://www.siemens.com/automation/Openness/SW/NetworkSource/FlgNet/v3">
              <Parts>
                <Access Scope="LiteralConstant" UId="21">
                  <Constant>
                    <ConstantType>Real</ConstantType>
                    <ConstantValue>200.0</ConstantValue>
                  </Constant>
                </Access>
                <Access Scope="GlobalVariable" UId="22">
                  <Symbol>
                    <Component Name="MELT_CONT_DB" />
                    <Component Name="mr_set" />
                  </Symbol>
                </Access>
                <Access Scope="LiteralConstant" UId="23">
                  <Constant>
                    <ConstantType>Real</ConstantType>
                    <ConstantValue>1200.0</ConstantValue>
                  </Constant>
                </Access>
                <Access Scope="GlobalVariable" UId="24">
                  <Symbol>
                    <Component Name="MELT_CONT_DB" />
                    <Component Name="mr_set" />
                  </Symbol>
                </Access>
                <Part Name="LIMIT" Version="1.0" UId="25" DisabledENO="true">
                  <TemplateValue Name="value_type" Type="Type">Real</TemplateValue>
                </Part>
              </Parts>
              <Wires>
                <Wire UId="27">
                  <OpenCon UId="26" />
                  <NameCon UId="25" Name="en" />
                </Wire>
                <Wire UId="28">
                  <IdentCon UId="21" />
                  <NameCon UId="25" Name="MN" />
                </Wire>
                <Wire UId="29">
                  <IdentCon UId="22" />
                  <NameCon UId="25" Name="IN" />
                </Wire>
                <Wire UId="30">
                  <IdentCon UId="23" />
                  <NameCon UId="25" Name="MX" />
                </Wire>
                <Wire UId="31">
                  <NameCon UId="25" Name="OUT" />
                  <IdentCon UId="24" />
                </Wire>
              </Wires>
            </FlgNet>
          </NetworkSource>
          <ProgrammingLanguage>FBD</ProgrammingLanguage>
        </AttributeList>
        <ObjectList>
          <MultilingualText ID="67" CompositionName="Comment">
            <ObjectList>
              <MultilingualTextItem ID="68" CompositionName="Items">
                <AttributeList>
                  <Culture>en-US</Culture>
                  <Text />
                </AttributeList>
              </MultilingualTextItem>
              <MultilingualTextItem ID="69" CompositionName="Items">
                <AttributeList>
                  <Culture>de-DE</Culture>
                  <Text />
                </AttributeList>
              </MultilingualTextItem>
            </ObjectList>
          </MultilingualText>
          <MultilingualText ID="6A" CompositionName="Title">
            <ObjectList>
              <MultilingualTextItem ID="6B" CompositionName="Items">
                <AttributeList>
                  <Culture>en-US</Culture>
                  <Text>Setpoint: MELTRATE limit</Text>
                </AttributeList>
              </MultilingualTextItem>
              <MultilingualTextItem ID="6C" CompositionName="Items">
                <AttributeList>
                  <Culture>de-DE</Culture>
                  <Text />
                </AttributeList>
              </MultilingualTextItem>
            </ObjectList>
          </MultilingualText>
        </ObjectList>
      </SW.Blocks.CompileUnit>
      <SW.Blocks.CompileUnit ID="6D" CompositionName="CompileUnits">
        <AttributeList>
          <NetworkSource>
            <FlgNet xmlns="http://www.siemens.com/automation/Openness/SW/NetworkSource/FlgNet/v3">
              <Parts>
                <Access Scope="LiteralConstant" UId="21">
                  <Constant>
                    <ConstantType>Real</ConstantType>
                    <ConstantValue>0.1</ConstantValue>
                  </Constant>
                </Access>
                <Access Scope="GlobalVariable" UId="22">
                  <Symbol>
                    <Component Name="MELT_CONT_DB" />
                    <Component Name="sw_set" />
                  </Symbol>
                </Access>
                <Access Scope="LiteralConstant" UId="23">
                  <Constant>
                    <ConstantType>Real</ConstantType>
                    <ConstantValue>1.0</ConstantValue>
                  </Constant>
                </Access>
                <Access Scope="GlobalVariable" UId="24">
                  <Symbol>
                    <Component Name="MELT_CONT_DB" />
                    <Component Name="sw_set" />
                  </Symbol>
                </Access>
                <Part Name="LIMIT" Version="1.0" UId="25" DisabledENO="true">
                  <TemplateValue Name="value_type" Type="Type">Real</TemplateValue>
                </Part>
              </Parts>
              <Wires>
                <Wire UId="27">
                  <OpenCon UId="26" />
                  <NameCon UId="25" Name="en" />
                </Wire>
                <Wire UId="28">
                  <IdentCon UId="21" />
                  <NameCon UId="25" Name="MN" />
                </Wire>
                <Wire UId="29">
                  <IdentCon UId="22" />
                  <NameCon UId="25" Name="IN" />
                </Wire>
                <Wire UId="30">
                  <IdentCon UId="23" />
                  <NameCon UId="25" Name="MX" />
                </Wire>
                <Wire UId="31">
                  <NameCon UId="25" Name="OUT" />
                  <IdentCon UId="24" />
                </Wire>
              </Wires>
            </FlgNet>
          </NetworkSource>
          <ProgrammingLanguage>FBD</ProgrammingLanguage>
        </AttributeList>
        <ObjectList>
          <MultilingualText ID="6E" CompositionName="Comment">
            <ObjectList>
              <MultilingualTextItem ID="6F" CompositionName="Items">
                <AttributeList>
                  <Culture>en-US</Culture>
                  <Text />
                </AttributeList>
              </MultilingualTextItem>
              <MultilingualTextItem ID="70" CompositionName="Items">
                <AttributeList>
                  <Culture>de-DE</Culture>
                  <Text />
                </AttributeList>
              </MultilingualTextItem>
            </ObjectList>
          </MultilingualText>
          <MultilingualText ID="71" CompositionName="Title">
            <ObjectList>
              <MultilingualTextItem ID="72" CompositionName="Items">
                <AttributeList>
                  <Culture>en-US</Culture>
                  <Text>Setpoint: SWING limit</Text>
                </AttributeList>
              </MultilingualTextItem>
              <MultilingualTextItem ID="73" CompositionName="Items">
                <AttributeList>
                  <Culture>de-DE</Culture>
                  <Text />
                </AttributeList>
              </MultilingualTextItem>
            </ObjectList>
          </MultilingualText>
        </ObjectList>
      </SW.Blocks.CompileUnit>
      <MultilingualText ID="74" CompositionName="Title">
        <ObjectList>
          <MultilingualTextItem ID="75" CompositionName="Items">
            <AttributeList>
              <Culture>en-US</Culture>
              <Text />
            </AttributeList>
          </MultilingualTextItem>
          <MultilingualTextItem ID="76" CompositionName="Items">
            <AttributeList>
              <Culture>de-DE</Culture>
              <Text />
            </AttributeList>
          </MultilingualTextItem>
        </ObjectList>
      </MultilingualText>
    </ObjectList>
  </SW.Blocks.FC>
</Document>